odoo/addons/purchase_invoice_plan_deposit/README.rst
odoo/addons/purchase_invoice_plan_deposit/__init__.py
odoo/addons/purchase_invoice_plan_deposit/__manifest__.py
odoo/addons/purchase_invoice_plan_deposit/i18n/es.po
odoo/addons/purchase_invoice_plan_deposit/i18n/it.po
odoo/addons/purchase_invoice_plan_deposit/i18n/purchase_invoice_plan_deposit.pot
odoo/addons/purchase_invoice_plan_deposit/models/__init__.py
odoo/addons/purchase_invoice_plan_deposit/models/purchase.py
odoo/addons/purchase_invoice_plan_deposit/readme/CONTRIBUTORS.rst
odoo/addons/purchase_invoice_plan_deposit/readme/DESCRIPTION.rst
odoo/addons/purchase_invoice_plan_deposit/readme/USAGE.rst
odoo/addons/purchase_invoice_plan_deposit/static/description/icon.png
odoo/addons/purchase_invoice_plan_deposit/static/description/index.html
odoo/addons/purchase_invoice_plan_deposit/tests/__init__.py
odoo/addons/purchase_invoice_plan_deposit/tests/test_purchase_invoice_plan.py
odoo/addons/purchase_invoice_plan_deposit/views/purchase_view.xml
odoo/addons/purchase_invoice_plan_deposit/wizard/__init__.py
odoo/addons/purchase_invoice_plan_deposit/wizard/purchase_create_invoice_plan.py
odoo/addons/purchase_invoice_plan_deposit/wizard/purchase_create_invoice_plan_view.xml
odoo/addons/purchase_invoice_plan_deposit/wizard/purchase_make_invoice_advance.py
odoo/addons/purchase_invoice_plan_deposit/wizard/purchase_make_planned_invoice.py
odoo14_addon_purchase_invoice_plan_deposit-14.0.1.0.1.dev7.dist-info/METADATA
odoo14_addon_purchase_invoice_plan_deposit-14.0.1.0.1.dev7.dist-info/WHEEL
odoo14_addon_purchase_invoice_plan_deposit-14.0.1.0.1.dev7.dist-info/top_level.txt
odoo14_addon_purchase_invoice_plan_deposit-14.0.1.0.1.dev7.dist-info/RECORD
